setup.py
TicTacToe_ClareWalker/TicTacToe.py
TicTacToe_ClareWalker/__init__.py
TicTacToe_ClareWalker.egg-info/PKG-INFO
TicTacToe_ClareWalker.egg-info/SOURCES.txt
TicTacToe_ClareWalker.egg-info/dependency_links.txt
TicTacToe_ClareWalker.egg-info/not-zip-safe
TicTacToe_ClareWalker.egg-info/top_level.txt