Metadata-Version: 1.0
Name: TicTacToe-ClareWalker
Version: 0.1
Summary: Command line tic tac toe
Home-page: UNKNOWN
Author: Clare Walker
Author-email: clare.walker.rsa@gmail.com
License: UNKNOWN
Platform: UNKNOWN
